{
    "os": "Linux-4.15.0-142-generic-x86_64-with-glibc2.17",
    "python": "3.8.17",
    "heartbeatAt": "2023-08-18T12:55:04.524344",
    "startedAt": "2023-08-18T12:55:03.156144",
    "docker": null,
    "cuda": "10.0.130",
    "args": [
        "--model",
        "deit_small_patch16_shrink_base",
        "--fuse_token",
        "--base_keep_rate",
        "0.7",
        "--input-size",
        "224",
        "--batch-size",
        "128",
        "--warmup-epochs",
        "5",
        "--shrink_start_epoch",
        "10",
        "--shrink_epochs",
        "100",
        "--epochs",
        "2",
        "--dist-eval",
        "--dataset_root_path",
        "../../data/cub/CUB_200_2011",
        "--dataset_name",
        "cub",
        "--output_dir",
        "."
    ],
    "state": "running",
    "program": "main.py",
    "codePath": "main.py",
    "host": "tesla",
    "username": "docker",
    "executable": "/home/docker/miniconda3/envs/evit/bin/python",
    "cpu_count": 24,
    "cpu_count_logical": 48,
    "cpu_freq": {
        "current": 1214.0760833333331,
        "min": 1000.0,
        "max": 3200.0
    },
    "cpu_freq_per_core": [
        {
            "current": 2660.271,
            "min": 1000.0,
            "max": 3200.0
        },
        {
            "current": 1000.012,
            "min": 1000.0,
            "max": 3200.0
        },
        {
            "current": 1001.29,
            "min": 1000.0,
            "max": 3200.0
        },
        {
            "current": 1000.899,
            "min": 1000.0,
            "max": 3200.0
        },
        {
            "current": 999.1,
            "min": 1000.0,
            "max": 3200.0
        },
        {
            "current": 999.447,
            "min": 1000.0,
            "max": 3200.0
        },
        {
            "current": 997.889,
            "min": 1000.0,
            "max": 3200.0
        },
        {
            "current": 1000.479,
            "min": 1000.0,
            "max": 3200.0
        },
        {
            "current": 999.834,
            "min": 1000.0,
            "max": 3200.0
        },
        {
            "current": 999.909,
            "min": 1000.0,
            "max": 3200.0
        },
        {
            "current": 999.594,
            "min": 1000.0,
            "max": 3200.0
        },
        {
            "current": 1000.257,
            "min": 1000.0,
            "max": 3200.0
        },
        {
            "current": 1553.674,
            "min": 1000.0,
            "max": 3200.0
        },
        {
            "current": 1001.089,
            "min": 1000.0,
            "max": 3200.0
        },
        {
            "current": 999.441,
            "min": 1000.0,
            "max": 3200.0
        },
        {
            "current": 1000.619,
            "min": 1000.0,
            "max": 3200.0
        },
        {
            "current": 1434.952,
            "min": 1000.0,
            "max": 3200.0
        },
        {
            "current": 999.655,
            "min": 1000.0,
            "max": 3200.0
        },
        {
            "current": 1359.978,
            "min": 1000.0,
            "max": 3200.0
        },
        {
            "current": 999.855,
            "min": 1000.0,
            "max": 3200.0
        },
        {
            "current": 999.07,
            "min": 1000.0,
            "max": 3200.0
        },
        {
            "current": 1702.323,
            "min": 1000.0,
            "max": 3200.0
        },
        {
            "current": 1000.008,
            "min": 1000.0,
            "max": 3200.0
        },
        {
            "current": 1543.986,
            "min": 1000.0,
            "max": 3200.0
        },
        {
            "current": 2653.494,
            "min": 1000.0,
            "max": 3200.0
        },
        {
            "current": 999.991,
            "min": 1000.0,
            "max": 3200.0
        },
        {
            "current": 999.819,
            "min": 1000.0,
            "max": 3200.0
        },
        {
            "current": 999.977,
            "min": 1000.0,
            "max": 3200.0
        },
        {
            "current": 1000.282,
            "min": 1000.0,
            "max": 3200.0
        },
        {
            "current": 999.954,
            "min": 1000.0,
            "max": 3200.0
        },
        {
            "current": 999.838,
            "min": 1000.0,
            "max": 3200.0
        },
        {
            "current": 1000.022,
            "min": 1000.0,
            "max": 3200.0
        },
        {
            "current": 1000.036,
            "min": 1000.0,
            "max": 3200.0
        },
        {
            "current": 1000.272,
            "min": 1000.0,
            "max": 3200.0
        },
        {
            "current": 1001.199,
            "min": 1000.0,
            "max": 3200.0
        },
        {
            "current": 1000.002,
            "min": 1000.0,
            "max": 3200.0
        },
        {
            "current": 1866.573,
            "min": 1000.0,
            "max": 3200.0
        },
        {
            "current": 999.998,
            "min": 1000.0,
            "max": 3200.0
        },
        {
            "current": 1000.0,
            "min": 1000.0,
            "max": 3200.0
        },
        {
            "current": 1000.0,
            "min": 1000.0,
            "max": 3200.0
        },
        {
            "current": 1695.293,
            "min": 1000.0,
            "max": 3200.0
        },
        {
            "current": 996.067,
            "min": 1000.0,
            "max": 3200.0
        },
        {
            "current": 1689.888,
            "min": 1000.0,
            "max": 3200.0
        },
        {
            "current": 1000.069,
            "min": 1000.0,
            "max": 3200.0
        },
        {
            "current": 999.634,
            "min": 1000.0,
            "max": 3200.0
        },
        {
            "current": 1487.623,
            "min": 1000.0,
            "max": 3200.0
        },
        {
            "current": 999.928,
            "min": 1000.0,
            "max": 3200.0
        },
        {
            "current": 1649.899,
            "min": 1000.0,
            "max": 3200.0
        }
    ],
    "disk": {
        "total": 937.8358497619629,
        "used": 781.9400405883789
    },
    "gpu": "GeForce RTX 2080 Ti",
    "gpu_count": 8,
    "gpu_devices": [
        {
            "name": "GeForce RTX 2080 Ti",
            "memory_total": 11554717696
        },
        {
            "name": "GeForce RTX 2080 Ti",
            "memory_total": 11554717696
        },
        {
            "name": "GeForce RTX 2080 Ti",
            "memory_total": 11554717696
        },
        {
            "name": "GeForce RTX 2080 Ti",
            "memory_total": 11554717696
        },
        {
            "name": "GeForce RTX 2080 Ti",
            "memory_total": 11554717696
        },
        {
            "name": "GeForce RTX 2080 Ti",
            "memory_total": 11554717696
        },
        {
            "name": "GeForce RTX 2080 Ti",
            "memory_total": 11554717696
        },
        {
            "name": "GeForce RTX 2080 Ti",
            "memory_total": 11554717696
        }
    ],
    "memory": {
        "total": 251.52594375610352
    }
}
